[
    {
        "name": "native api",
        "link": "native-api/"
    },
    {
        "name": "javascript",
        "link": "javascript/"
    },
    {
        "name": "cascading style sheets",
        "link": "cascading-style-sheets/"
    },
    {
        "name": "HTML",
        "link": "html/"
    },
    {
        "name": "webvr",
        "link": "webvr/"
    },
    {
        "name": "three.js",
        "link": "three-js/"
    },
    {
        "name": "webgl",
        "link": "webgl/"
    },
    {
        "name": "benchmark",
        "link": "benchmark/"
    },
    {
        "name": "react-native",
        "link": "react-native/"
    },
    {
        "name": "tinymce",
        "link": "tinymce/"
    },
    {
        "name": "pitfall",
        "link": "pitfall/"
    },
    {
        "name": "ECMAScript 6",
        "link": "ecma-script-6/"
    },
    {
        "name": "bubble sort",
        "link": "bubble-sort/"
    },
    {
        "name": "quick sort",
        "link": "quick-sort/"
    },
    {
        "name": "echarts",
        "link": "echarts/"
    },
    {
        "name": "amap",
        "link": "amap/"
    },
    {
        "name": "bmap",
        "link": "bmap/"
    },
    {
        "name": "angular js",
        "link": "angular/"
    },
    {
        "name": "async js",
        "link": "async/"
    },
    {
        "name": "bootstrap datetimepicker",
        "link": "bootstrap-datetimepicker/"
    },
    {
        "name": "knockout js",
        "link": "knockout/"
    },
    {
        "name": "mathjax",
        "link": "mathjax/"
    },
    {
        "name": "moment",
        "link": "moment/"
    },
    {
        "name": "underscore",
        "link": "underscore/"
    },
    {
        "name": "baidu map",
        "link": "baidu-map/"
    },
    {
        "name": "dp share",
        "link": "dp-share/"
    },
    {
        "name": "qrcode",
        "link": "qrcode/"
    },
    {
        "name": "wechat share",
        "link": "wechat-share/"
    },
    {
        "name": "react js",
        "link": "react/"
    },
    {
        "name": "hammer",
        "link": "hammer/"
    },
    {
        "name": "browserify",
        "link": "browserify/"
    },
    {
        "name": "angular material",
        "link": "angular-material/"
    },
    {
        "name": "layout",
        "link": "layout/"
    },
    {
        "name": "koa",
        "link": "koa/"
    },
    {
        "name": "react redux",
        "link": "react-redux/release/"
    },
    {
        "name": "sliding tiles puzzle",
        "link": "sliding-tiles-puzzle/"
    },
    {
        "name": "on screen",
        "link": "on-screen/"
    },
    {
        "name": "qq maps",
        "link": "qq-maps/"
    },
    {
        "name": "babel-plugin-import",
        "link": "babel-plugin-import/"
    },
    {
        "name": "dragula",
        "link": "dragula/"
    },
    {
        "name": "mobx",
        "link": "mobx/"
    }
]
